aiotg/__init__.py
aiotg/bot.py
aiotg/chat.py
aiotg-0.7.12.dist-info/DESCRIPTION.rst
aiotg-0.7.12.dist-info/METADATA
aiotg-0.7.12.dist-info/RECORD
aiotg-0.7.12.dist-info/WHEEL
aiotg-0.7.12.dist-info/metadata.json
aiotg-0.7.12.dist-info/top_level.txt
