Metadata-Version: 2.0
Name: aiotg
Version: 0.7.12
Summary: Asynchronous Python API for building Telegram bots
Home-page: https://github.com/szastupov/aiotg
Author: Stepan Zastupov
Author-email: stepan.zastupov@gmail.com
License: MIT
Keywords: asyncio telegram
Platform: UNKNOWN
Classifier: Development Status :: 4 - Beta
Classifier: Intended Audience :: Developers
Classifier: License :: OSI Approved :: MIT License
Classifier: Programming Language :: Python :: 3.5
Classifier: Topic :: Software Development
Classifier: Topic :: Software Development :: Libraries
Requires-Dist: aiohttp (>=0.17.2)
